ztv/__about__.py
ztv/__init__.py
ztv/astropy_helpers_git_helpers.py
ztv/color_panel.py
ztv/default_panels.py
ztv/file_picker.py
ztv/fits_header_dialog.py
ztv/image_process_action.py
ztv/phot_panel.py
ztv/plot_panel.py
ztv/quick_phot.py
ztv/source_panel.py
ztv/stats_panel.py
ztv/ztv.py
ztv/ztv_api.py
ztv/ztv_lib.py
ztv/ztv_wx_lib.py
ztv-0.2.3.post4.dist-info/DESCRIPTION.rst
ztv-0.2.3.post4.dist-info/METADATA
ztv-0.2.3.post4.dist-info/RECORD
ztv-0.2.3.post4.dist-info/WHEEL
ztv-0.2.3.post4.dist-info/metadata.json
ztv-0.2.3.post4.dist-info/pbr.json
ztv-0.2.3.post4.dist-info/top_level.txt
ztv_examples/__init__.py
ztv_examples/fits_faker_panel/__init__.py
ztv_examples/fits_faker_panel/control_panels.py
ztv_examples/fits_faker_panel/fake_fits_maker.py
ztv_examples/fits_faker_panel/fits_faker_panel.py
ztv_examples/fits_faker_panel/launch_ztv.py
