Metadata-Version: 2.0
Name: ztv
Version: 0.2.3.post4
Summary: Simple python image viewer, largely intended for astronomical applications
Home-page: https://github.com/henryroe/ztv
Author: Henry Roe
Author-email: hroe@hroe.me
License: MIT License
Keywords: astronomy image viewer fits
Platform: UNKNOWN
Classifier: Development Status :: 4 - Beta
Classifier: Intended Audience :: Science/Research
Classifier: Topic :: Multimedia :: Graphics :: Viewers
Classifier: Topic :: Scientific/Engineering :: Astronomy
Classifier: License :: OSI Approved :: MIT License
Classifier: Programming Language :: Python :: 2
Classifier: Programming Language :: Python :: 2.7
Requires-Dist: astropy (>=1.0.0)
Requires-Dist: astropy-helpers (>=1.0.0)
Requires-Dist: matplotlib (>=1.5.1)
Requires-Dist: psutil (>=2.0)
Requires-Dist: wxPython (>=3.0)
